rankfx/__init__.py
rankfx/common/__init__.py
rankfx/common/base/__init__.py
rankfx/common/base/model.py
rankfx/common/base/config/__init__.py
rankfx/common/base/config/base_config.py
rankfx/common/base/config/training_config.py
rankfx/common/features/__init__.py
rankfx/common/features/config.py
rankfx/common/features/types.py
rankfx/common/features/datasets/__init__.py
rankfx/common/features/datasets/pandas.py
rankfx/common/modules/__init__.py
rankfx/common/modules/crossnet.py
rankfx/common/modules/embedding.py
rankfx/common/modules/finalnet.py
rankfx/common/modules/mlp.py
rankfx/common/utils/__init__.py
rankfx/common/utils/import_utils.py
rankfx/common/utils/logging_utils.py
rankfx/common/utils/training_utils.py
rankfx/dcnv2/__init__.py
rankfx/dcnv2/model.py
rankfx/dcnv2/config/__init__.py
rankfx/dcnv2/config/model_config.py
rankfx/finalnet/__init__.py
rankfx/finalnet/model.py
rankfx-1.0.0.dist-info/LICENSE
rankfx-1.0.0.dist-info/METADATA
rankfx-1.0.0.dist-info/WHEEL
rankfx-1.0.0.dist-info/top_level.txt
rankfx-1.0.0.dist-info/RECORD
