Metadata-Version: 2.1
Name: rankfx
Version: 1.0.0
Home-page: https://github.com/sn09/rankfx
Author: Saraev Nikita
Author-email: saraevnik0909@gmail.com
License: Apache
Requires-Python: >=3.10
License-File: LICENSE
